README.md
setup.cfg
setup.py
ophardtImport/__init__.py
ophardtImport/models.py
ophardtImport/ophardtImport.py
ophardtimport.egg-info/PKG-INFO
ophardtimport.egg-info/SOURCES.txt
ophardtimport.egg-info/dependency_links.txt
ophardtimport.egg-info/requires.txt
ophardtimport.egg-info/top_level.txt