Metadata-Version: 1.0
Name: ophardtimport
Version: 1.1
Summary: Allows python to interact with Ophardt file exports
Home-page: https://github.com/Phill93/ophardtimport
Author: Phill93
Author-email: phill93@phill93.de
License: GPLv3
Platform: UNKNOWN
